server/__init__.py
server/server_run.py
server/common/__init__.py
server/common/decorate.py
server/common/descryptors.py
server/common/errors.py
server/common/metaclasses.py
server/common/utils.py
server/common/variables.py
server/proj_log/__init__.py
server/server/__init__.py
server/server/add_user.py
server/server/config_window.py
server/server/core.py
server/server/main_window.py
server/server/remove_user.py
server/server/server_db.py
server/server/stat_window.py
server/unit_tests/__init__.py
py_CS_august_server-0.0.1.dist-info/METADATA
py_CS_august_server-0.0.1.dist-info/WHEEL
py_CS_august_server-0.0.1.dist-info/top_level.txt
py_CS_august_server-0.0.1.dist-info/RECORD
